telemetry/__init__.py
wise_telemetry-1.2.dist-info/METADATA
wise_telemetry-1.2.dist-info/WHEEL
wise_telemetry-1.2.dist-info/top_level.txt
wise_telemetry-1.2.dist-info/RECORD
