Metadata-Version: 2.1
Name: wise-telemetry
Version: 1.2
Author: Carlo Moro
Author-email: Carlo Moro <carlo.moro@wises.com.br>
Classifier: Programming Language :: Python :: 3
Classifier: License :: OSI Approved :: MIT License
Classifier: Operating System :: OS Independent
Requires-Python: >=3.7
Requires-Dist: requests
